__init__.py
supervisor_tee.py
supervisor_tee-0.1.0.dist-info/METADATA
supervisor_tee-0.1.0.dist-info/WHEEL
supervisor_tee-0.1.0.dist-info/entry_points.txt
supervisor_tee-0.1.0.dist-info/top_level.txt
supervisor_tee-0.1.0.dist-info/RECORD
