Metadata-Version: 2.1
Name: supervisor-tee
Version: 0.1.0
Summary: A brief description of your project
Author-email: Teo <teocns@gmail.com>
Classifier: Programming Language :: Python :: 3
Classifier: License :: OSI Approved :: MIT License
Classifier: Operating System :: OS Independent
Requires-Python: >=3.11
Requires-Dist: supervisor>=4.2.5
